khashimoto_echo_dt/__init__.py
khashimoto_echo_dt/__main__.py
khashimoto_echo_dt/main.py
khashimoto_echo_dt/py.typed
khashimoto_echo_dt-0.1.6.dist-info/METADATA
khashimoto_echo_dt-0.1.6.dist-info/WHEEL
khashimoto_echo_dt-0.1.6.dist-info/entry_points.txt
khashimoto_echo_dt-0.1.6.dist-info/RECORD
